odoo/addons/product_uom_updatable/README.rst
odoo/addons/product_uom_updatable/__init__.py
odoo/addons/product_uom_updatable/__manifest__.py
odoo/addons/product_uom_updatable/i18n/ca.po
odoo/addons/product_uom_updatable/i18n/es.po
odoo/addons/product_uom_updatable/i18n/it.po
odoo/addons/product_uom_updatable/i18n/product_uom_updatable.pot
odoo/addons/product_uom_updatable/models/__init__.py
odoo/addons/product_uom_updatable/models/product_template.py
odoo/addons/product_uom_updatable/readme/CONTRIBUTORS.rst
odoo/addons/product_uom_updatable/readme/DESCRIPTION.rst
odoo/addons/product_uom_updatable/static/description/icon.png
odoo/addons/product_uom_updatable/static/description/index.html
odoo/addons/product_uom_updatable/tests/__init__.py
odoo/addons/product_uom_updatable/tests/test_product_uom_update.py
odoo13_addon_product_uom_updatable-13.0.1.0.1.dev10.dist-info/METADATA
odoo13_addon_product_uom_updatable-13.0.1.0.1.dev10.dist-info/WHEEL
odoo13_addon_product_uom_updatable-13.0.1.0.1.dev10.dist-info/top_level.txt
odoo13_addon_product_uom_updatable-13.0.1.0.1.dev10.dist-info/RECORD
