Metadata-Version: 2.1
Name: odoo13-addon-product-uom-updatable
Version: 13.0.1.0.1.dev10
Summary: allows products uom to be modified after be used in a stock picking if the product uom is of the same category
Home-page: https://github.com/OCA/product-attribute
Author: ACSONE SA/NV, Camptocamp, Odoo Community Association (OCA)
Author-email: support@odoo-community.org
License: AGPL-3
Platform: UNKNOWN
Classifier: Programming Language :: Python
Classifier: Framework :: Odoo
Classifier: Framework :: Odoo :: 13.0
Classifier: License :: OSI Approved :: GNU Affero General Public License v3
Requires-Python: >=3.5
Requires-Dist: odoo <13.1dev,>=13.0a
